<?xml version="1.0" encoding="utf-8"?>
<annotations>
  <version>1.1</version>
  <meta>
    <task>
      <id>196</id>
      <name>target_toystore</name>
      <size>1</size>
      <mode>annotation</mode>
      <overlap>0</overlap>
      <bugtracker></bugtracker>
      <flipped>False</flipped>
      <created>2019-04-06 02:32:34.921802+03:00</created>
      <updated>2019-05-14 05:36:14.539674+03:00</updated>
      <source>1 images: target_toystore.png, ...</source>
      <labels>
        <label>
          <name>toys</name>
          <attributes>
          </attributes>
        </label>
        <label>
          <name>wall</name>
          <attributes>
          </attributes>
        </label>
        <label>
          <name>stuffed_animal</name>
          <attributes>
          </attributes>
        </label>
        <label>
          <name>shelf</name>
          <attributes>
          </attributes>
        </label>
        <label>
          <name>toy</name>
          <attributes>
          </attributes>
        </label>
        <label>
          <name>ceiling_light</name>
          <attributes>
          </attributes>
        </label>
        <label>
          <name>ceiling</name>
          <attributes>
          </attributes>
        </label>
        <label>
          <name>floor</name>
          <attributes>
          </attributes>
        </label>
      </labels>
      <segments>
        <segment>
          <id>196</id>
          <start>0</start>
          <stop>0</stop>
          <url>http://olive.cmb.ucdavis.edu/?id=196</url>
        </segment>
      </segments>
      <owner>
        <username>RA</username>
        <email></email>
      </owner>
    </task>
    <dumped>2019-06-02 18:39:15.119744+03:00</dumped>
  </meta>
  <image id="0" name="target_toystore.png" width="1024" height="768">
    <polygon label="shelf" points="327.93,494.06;574.04,735.30;606.20,741.63;751.57,686.71;792.22,652.01;757.81,583.49;723.11,562.58;728.72,499.42;760.05,489.82;760.35,484.76;714.97,465.21;715.85,395.48;757.96,391.58;768.34,385.09;766.78,380.22;719.56,367.06;720.53,320.28;776.38,305.71;777.06,300.83;721.99,288.80;722.82,251.52;755.52,249.18;755.28,241.91;732.91,239.58;501.00,233.20;349.23,229.97;349.47,297.67;339.82,358.10;343.67,415.46" occluded="1" client_id="10" z_order="11">
    </polygon>
    <polygon label="toy" points="454.88,234.87;455.16,186.93;530.18,184.39;530.74,238.25;489.57,238.54" occluded="0" client_id="29" z_order="30">
    </polygon>
    <polygon label="ceiling_light" points="815.78,55.93;894.94,71.60;946.19,63.93;867.19,46.30" occluded="0" client_id="2" z_order="3">
    </polygon>
    <polygon label="toys" points="28.20,341.80;59.25,342.31;64.94,352.87;78.75,405.67;86.46,444.25;88.90,473.90;93.77,488.92;102.30,514.91;110.42,568.52;133.86,641.54;148.44,697.10;147.30,751.20;155.10,754.60;166.83,768.00;0.00,768.00;0.00,378.13;0.00,346.94" occluded="0" client_id="20" z_order="21">
    </polygon>
    <polygon label="toys" points="268.59,273.35;291.03,276.61;348.02,273.21;349.24,248.59;343.39,246.42;346.66,204.39;336.45,199.22;358.76,186.71;360.66,162.37;336.05,158.42;311.84,159.10;281.64,160.19;277.00,197.70;264.30,199.90;264.50,221.30;281.37,225.20;282.19,249.00;267.30,252.00;264.30,256.20;265.50,270.00" occluded="0" client_id="49" z_order="50">
    </polygon>
    <polygon label="ceiling_light" points="638.80,0.00;760.58,25.00;713.91,37.24;599.01,17.66" occluded="1" client_id="4" z_order="5">
    </polygon>
    <polygon label="toy" points="377.37,303.03;395.00,308.58;419.15,315.76;426.82,315.43;453.88,322.81;475.67,322.89;503.48,330.53;511.51,344.24;554.83,356.89;607.48,355.94;607.23,284.51;539.78,267.81;478.18,262.47;477.96,246.61;427.41,243.67;414.83,244.91;392.96,247.07;372.30,250.80;372.44,276.87;376.52,279.59" occluded="1" client_id="36" z_order="37">
    </polygon>
    <polygon label="ceiling" points="1024.00,104.63;726.52,47.13;473.30,0.00;1024.00,0.00" occluded="1" client_id="1" z_order="2">
    </polygon>
    <polygon label="toys" points="923.40,185.25;919.67,237.16;960.22,240.48;1024.00,242.44;1024.00,141.19;995.86,135.70;980.78,132.18;973.53,131.00;961.78,151.37;959.04,157.64;945.60,159.10;944.60,183.10;927.70,183.88" occluded="0" client_id="25" z_order="26">
    </polygon>
    <polygon label="toy" points="362.69,229.79;406.01,231.82;404.32,149.59;391.12,149.92;359.99,153.99" occluded="1" client_id="27" z_order="28">
    </polygon>
    <polygon label="toys" points="590.25,97.86;690.93,108.30;806.53,121.64;809.58,70.87;759.49,50.91;617.01,27.22;594.00,23.15" occluded="1" client_id="52" z_order="53">
    </polygon>
    <polygon label="toys" points="812.64,119.94;891.83,132.12;969.33,141.94;972.04,97.60;885.06,82.04;884.05,72.56;816.02,58.01;788.95,62.74;784.50,116.90" occluded="1" client_id="53" z_order="54">
    </polygon>
    <polygon label="toys" points="106.39,153.63;165.34,152.06;212.15,155.78;266.79,158.52;264.44,199.06;264.63,238.43;263.46,273.88;255.23,314.61;216.65,312.46;213.32,326.76;176.11,327.93;167.69,321.86;167.10,315.79;145.89,314.48;132.51,311.05;132.36,277.93;104.11,277.93;97.75,273.68;95.95,270.59;93.80,225.30;93.56,200.65;99.28,198.61;105.66,198.20;105.00,156.66" occluded="0" client_id="26" z_order="27">
    </polygon>
    <polygon label="stuffed_animal" points="796.25,126.35;800.48,116.24;812.00,108.49;829.62,104.26;832.21,104.02;845.84,114.83;859.47,132.69;862.05,144.21;853.83,152.43;847.72,155.25;852.42,165.13;859.70,172.41;880.39,181.81;885.79,209.78;872.87,222.71;834.09,223.18;790.60,222.00;791.55,164.19;798.13,156.19;799.30,153.37;795.07,138.10" occluded="1" client_id="8" z_order="9">
    </polygon>
    <polygon label="wall" points="46.46,475.80;1024.00,362.81;1024.00,105.97;470.04,0.00;0.00,0.00" occluded="1" client_id="89" z_order="56">
    </polygon>
    <polygon label="toy" points="602.16,0.00;601.18,49.61;594.85,68.13;588.02,106.63;585.73,143.86;588.85,146.84;589.00,198.25;633.49,199.76;631.98,146.98;636.46,144.54;636.32,105.36;637.34,66.67;629.88,64.96;629.30,43.13;631.59,40.16;631.74,12.52;627.25,7.80;627.11,0.00" occluded="1" client_id="32" z_order="33">
    </polygon>
    <polygon label="toys" points="748.18,388.86;798.67,401.26;822.64,412.55;859.30,422.42;886.94,417.06;889.76,367.70;850.28,353.04;817.84,347.12;804.31,349.65;799.51,360.09;750.72,350.50" occluded="1" client_id="42" z_order="43">
    </polygon>
    <polygon label="toys" points="111.30,133.60;251.00,138.84;471.70,146.80;470.40,110.40;428.23,87.40;306.73,77.92;287.78,83.34;175.42,77.58;165.83,87.09;110.33,83.00" occluded="0" client_id="50" z_order="51">
    </polygon>
    <polygon label="toys" points="101.40,341.30;106.35,385.05;228.47,376.59;300.38,367.28;342.97,361.64;341.62,320.35;293.56,321.03;281.71,327.80;174.09,336.93" occluded="0" client_id="45" z_order="46">
    </polygon>
    <polygon label="toy" points="405.76,232.20;457.30,235.70;450.90,209.70;432.09,199.06;406.00,197.65;405.53,210.58;403.18,228.44" occluded="0" client_id="28" z_order="29">
    </polygon>
    <polygon label="toy" points="643.63,222.83;719.85,224.46;715.11,301.50;658.81,305.25;641.51,298.39" occluded="1" client_id="18" z_order="19">
    </polygon>
    <polygon label="toy" points="646.89,160.95;691.20,166.20;689.00,238.70;639.06,237.33;641.21,160.75" occluded="1" client_id="31" z_order="32">
    </polygon>
    <polygon label="toys" points="571.85,594.30;620.97,628.84;708.40,603.46;709.57,581.84;729.79,577.14;734.72,516.03;707.22,501.23;612.04,526.38;572.79,535.31" occluded="0" client_id="14" z_order="15">
    </polygon>
    <polygon label="toy" points="722.32,673.65;802.22,647.01;805.55,599.62;755.02,573.57;679.80,598.20;680.01,649.17" occluded="1" client_id="13" z_order="14">
    </polygon>
    <polygon label="toys" points="1.67,336.99;22.78,334.56;23.60,321.16;42.68,319.94;75.58,313.03;71.52,240.75;0.00,243.59" occluded="0" client_id="46" z_order="47">
    </polygon>
    <polygon label="toys" points="91.20,405.70;172.77,392.49;262.73,383.47;265.84,405.18;310.40,403.77;321.40,411.39;321.96,453.13;209.71,468.08;186.59,472.31;170.51,468.08;108.47,482.74;95.78,479.08" occluded="0" client_id="44" z_order="45">
    </polygon>
    <polygon label="toy" points="426.03,229.83;430.12,188.31;431.88,156.14;434.22,128.07;434.22,98.25;442.41,47.37;452.50,47.20;456.44,53.22;465.80,90.06;471.06,152.05;475.74,233.34" occluded="1" client_id="38" z_order="39">
    </polygon>
    <polygon label="stuffed_animal" points="560.52,0.00;546.66,74.88;524.80,165.13;505.01,218.78;584.40,216.70;603.70,58.36;604.92,12.48;604.10,0.00" occluded="1" client_id="5" z_order="6">
    </polygon>
    <polygon label="toy" points="662.80,478.30;688.67,488.78;742.67,477.22;742.67,457.36;731.92,407.59;716.69,402.69;664.19,410.44" occluded="0" client_id="15" z_order="16">
    </polygon>
    <polygon label="toy" points="970.30,304.21;1016.68,308.56;1024.00,305.70;1024.00,259.46;972.89,259.46;970.17,264.09;968.26,304.07" occluded="0" client_id="24" z_order="25">
    </polygon>
    <polygon label="toys" points="343.47,358.77;362.09,368.58;369.53,361.14;397.96,371.97;412.85,370.61;463.61,394.30;503.55,409.87;515.39,409.53;569.54,433.90;614.20,425.10;614.00,373.00;465.60,331.70;405.74,313.08;377.65,310.04;363.44,319.17;344.15,323.57" occluded="1" client_id="35" z_order="36">
    </polygon>
    <polygon label="floor" points="45.20,474.30;597.70,410.40;1024.00,362.70;1024.00,768.00;50.86,768.00" occluded="1" client_id="0" z_order="1">
    </polygon>
    <polygon label="toys" points="335.30,489.10;358.03,502.52;388.58,529.08;415.85,562.45;447.62,592.63;462.19,599.44;482.87,615.42;485.69,633.05;522.59,676.53;555.26,667.60;605.79,654.34;584.82,552.49;395.82,425.88;356.81,438.57;336.83,458.08" occluded="1" client_id="33" z_order="34">
    </polygon>
    <polygon label="stuffed_animal" points="850.40,236.90;897.61,237.81;906.04,235.09;910.80,230.19;923.04,189.53;923.04,183.00;919.10,172.53;891.49,162.32;881.56,163.14;877.34,166.27;874.35,173.48;874.89,183.00;878.16,194.97;873.40,193.33;870.54,191.57;867.69,186.13;861.16,185.45;857.48,187.08;854.49,192.38;854.36,199.59;859.52,204.62;872.45,207.34;870.81,211.29;861.97,215.37;855.58,215.78;849.87,215.64;844.00,220.50;840.60,227.60;842.50,234.50" occluded="0" client_id="6" z_order="7">
    </polygon>
    <polygon label="toy" points="571.98,304.11;610.33,310.31;659.13,305.90;659.13,290.40;651.79,270.32;645.75,247.15;639.71,235.07;585.85,236.54;578.18,258.25;572.14,289.74" occluded="0" client_id="17" z_order="18">
    </polygon>
    <polygon label="toys" points="235.80,0.37;237.21,63.82;353.69,75.95;474.11,86.10;590.93,97.47;592.62,23.01;472.48,1.86;438.52,0.00" occluded="1" client_id="51" z_order="52">
    </polygon>
    <polygon label="toys" points="742.20,321.62;768.43,327.54;804.53,330.93;822.30,334.31;858.12,339.95;887.73,334.31;884.91,268.88;837.25,264.37;819.48,268.60;817.22,271.42;814.12,287.50;796.63,283.55;794.38,251.11;721.62,247.73;717.10,316.83" occluded="1" client_id="37" z_order="38">
    </polygon>
    <polygon label="toy" points="541.92,205.80;543.88,235.37;548.77,240.27;625.55,241.84;628.09,208.74;631.62,205.80;634.16,195.42;600.28,184.45;581.68,177.40;558.96,174.27;556.80,186.41;544.07,185.63;540.16,192.87" occluded="0" client_id="30" z_order="31">
    </polygon>
    <polygon label="toys" points="913.32,481.79;902.49,559.63;971.19,584.67;1024.00,560.64;1024.00,447.10" occluded="1" client_id="21" z_order="22">
    </polygon>
    <polygon label="toy" points="0.00,204.90;46.18,205.33;36.43,88.78;0.00,88.37" occluded="0" client_id="47" z_order="48">
    </polygon>
    <polygon label="toy" points="715.11,299.54;734.54,302.96;771.59,301.98;771.59,285.83;764.90,267.50;716.26,267.06" occluded="1" client_id="19" z_order="20">
    </polygon>
    <polygon label="ceiling_light" points="968.55,83.99;1024.00,77.95;1024.00,95.57" occluded="0" client_id="3" z_order="4">
    </polygon>
    <polygon label="wall" points="50.44,768.00;45.57,474.22;0.00,0.00;0.00,768.00" occluded="1" client_id="90" z_order="57">
    </polygon>
    <polygon label="toy" points="0.45,87.64;35.93,88.81;45.81,80.35;47.45,71.66;46.75,53.56;81.76,56.38;85.29,48.16;75.89,0.00;0.00,0.00" occluded="0" client_id="48" z_order="49">
    </polygon>
    <polygon label="shelf" points="752.94,496.21;989.30,586.37;993.68,585.88;1024.00,569.80;1024.00,241.33;791.92,231.10;681.79,226.71;673.99,374.86;663.10,462.10" occluded="1" client_id="11" z_order="12">
    </polygon>
    <polygon label="toys" points="363.19,418.30;376.45,431.55;405.21,461.73;428.62,481.11;437.79,478.74;456.12,491.43;481.27,508.83;498.68,506.94;553.87,544.50;606.75,536.04;614.02,472.81;476.31,399.26;406.23,361.78;361.72,372.19;359.52,374.90;360.51,414.77" occluded="1" client_id="34" z_order="35">
    </polygon>
    <polygon label="toy" points="988.02,458.58;1024.00,464.95;1024.00,401.62;990.46,407.66" occluded="0" client_id="22" z_order="23">
    </polygon>
    <polygon label="toys" points="504.40,43.38;523.01,42.81;527.53,83.70;528.94,145.47;532.32,161.54;539.09,233.46;493.40,233.74;495.09,161.26;500.45,134.19;500.45,102.88;502.14,73.55" occluded="1" client_id="39" z_order="40">
    </polygon>
    <polygon label="toy" points="925.86,371.93;915.71,439.62;932.91,446.95;945.60,446.95;970.98,439.34;976.34,372.78" occluded="1" client_id="41" z_order="42">
    </polygon>
    <polygon label="stuffed_animal" points="860.35,340.35;958.47,357.78;963.76,284.53;949.07,283.94;943.20,290.02;885.42,285.90;875.63,285.90;873.67,286.29;868.97,300.20;861.33,312.93" occluded="0" client_id="7" z_order="8">
    </polygon>
    <polygon label="toy" points="955.37,379.75;1011.68,391.83;1015.44,391.67;1024.00,387.59;1024.00,315.12;989.65,315.94;960.60,326.71" occluded="1" client_id="23" z_order="24">
    </polygon>
    <polygon label="toys" points="717.90,228.40;774.04,229.94;793.55,211.61;797.31,187.64;793.55,171.19;750.30,165.78;705.88,170.01;700.24,175.89;697.66,195.40;682.15,207.38;681.00,226.80" occluded="1" client_id="43" z_order="44">
    </polygon>
    <polygon label="toy" points="948.07,768.00;960.41,661.72;963.35,656.24;983.13,648.99;989.40,647.42;1007.81,647.03;1010.74,640.57;1013.49,639.39;1014.86,632.34;1006.63,632.15;1000.36,628.82;998.99,620.40;1001.54,614.72;1024.00,599.05;1024.00,768.00" occluded="0" client_id="9" z_order="10">
    </polygon>
    <polygon label="toy" points="575.10,352.50;575.60,386.30;602.31,397.40;757.03,376.51;757.68,344.52;727.32,338.32" occluded="0" client_id="16" z_order="17">
    </polygon>
    <polygon label="toy" points="580.13,634.28;579.54,681.29;624.78,724.37;717.42,689.51;718.99,639.76;670.61,606.67" occluded="1" client_id="12" z_order="13">
    </polygon>
    <polygon label="toy" points="471.87,148.53;602.78,156.99;767.06,166.39;768.00,133.96;706.66,126.44;703.60,120.57;666.71,117.28;662.48,109.28;501.72,93.77;475.87,98.47;463.41,100.12;462.47,147.36" occluded="1" client_id="54" z_order="55">
    </polygon>
    <polygon label="toys" points="747.32,406.28;797.75,422.19;812.98,415.08;960.70,461.80;957.30,523.70;923.64,543.01;857.99,521.69;839.37,518.30;799.78,502.74;718.55,469.23;698.25,460.43;704.68,393.76" occluded="1" client_id="40" z_order="41">
    </polygon>
  </image>
</annotations>